purecl/__init__.py
purecl/_cffi.py
purecl/_py.py
purecl/blas/__init__.py
purecl/blas/_clblas.py
purecl/common/__init__.py
purecl/common/const.py
purecl/common/errors.py
purecl/common/ocl_api.c
purecl/common/src_reader.py
purecl-0.3.dist-info/LICENSE
purecl-0.3.dist-info/METADATA
purecl-0.3.dist-info/WHEEL
purecl-0.3.dist-info/top_level.txt
purecl-0.3.dist-info/RECORD
